kamcp/__init__.py
kamcp/__main__.py
kamcp/py.typed
kamcp/server/__init__.py
kamcp/server/executor.py
kamcp/server/initializer.py
kamcp-0.1.4.dist-info/WHEEL
kamcp-0.1.4.dist-info/entry_points.txt
kamcp-0.1.4.dist-info/METADATA
kamcp-0.1.4.dist-info/RECORD
